{"Splash":[{"title":"Blogs","type":"sitelink","link":"/posts"},{"title":"Google","type":"permalink","link":"https://www.google.com","_blank":true},{"title":"Github","type":"permalink","link":"https://github.com/lan2lang/lan2lang","_blank":true},{"title":"Rss","type":"permalink","link":"/atom.xml","_blank":true}],"Drawer":[{"title":"标签","type":"sitelink","link":"/tags"},{"title":"关于","type":"page","link":"/about","layout":"about"}],"animated":{"posts":"rotateInDownLeft","post":"slideInLeft","page":"slideInLeft","tags":"bounceInUp"},"page404":true}